easyscrape_googlesuggest/__init__.py
easyscrape_googlesuggest/getsuggestions.py
easyscrape_googlesuggest-0.1.2.dist-info/LICENSE
easyscrape_googlesuggest-0.1.2.dist-info/METADATA
easyscrape_googlesuggest-0.1.2.dist-info/WHEEL
easyscrape_googlesuggest-0.1.2.dist-info/top_level.txt
easyscrape_googlesuggest-0.1.2.dist-info/RECORD
