Metadata-Version: 2.1
Name: easyscrape-googlesuggest
Version: 0.1.2
Summary: Easy web scraping wrapper for Google Suggest results
Home-page: https://github.com/amazingjoe/EasyScrape-GoogleSuggest
Author: Joseph Ucuzoglu
Author-email: baldmancodes@gmail.com
Classifier: Programming Language :: Python :: 3
Classifier: License :: OSI Approved :: MIT License
Classifier: Operating System :: OS Independent
Requires-Python: >=3.7
License-File: LICENSE
